mlcube/__init__.py
mlcube/__main__.py
mlcube/cli.py
mlcube/config.py
mlcube/errors.py
mlcube/parser.py
mlcube/platform.py
mlcube/runner.py
mlcube/shell.py
mlcube/system_settings.py
mlcube/validate.py
mlcube/tests/__init__.py
mlcube/tests/test_cli.py
mlcube/tests/test_config.py
mlcube/tests/test_errors.py
mlcube/tests/test_mlcommons_mlcube_cli.py
mlcube/tests/test_parser.py
mlcube/tests/test_shell.py
mlcube-0.0.9.dist-info/METADATA
mlcube-0.0.9.dist-info/WHEEL
mlcube-0.0.9.dist-info/entry_points.txt
mlcube-0.0.9.dist-info/top_level.txt
mlcube-0.0.9.dist-info/RECORD
