Metadata-Version: 2.1
Name: mlcube
Version: 0.0.9
License: Apache 2.0
Requires-Python: >=3.6
Requires-Dist: click (<9.0.0,>=8.0.0)
Requires-Dist: coloredlogs (==14.0)
Requires-Dist: cookiecutter (==2.1.1)
Requires-Dist: omegaconf (==2.1.0)
Requires-Dist: markdown
